pyconza2014/__init__.py
pyconza2014/__main__.py
pyconza2014/cli.py
pyconza2014-0.2.10.dist-info/DESCRIPTION.rst
pyconza2014-0.2.10.dist-info/entry_points.txt
pyconza2014-0.2.10.dist-info/METADATA
pyconza2014-0.2.10.dist-info/metadata.json
pyconza2014-0.2.10.dist-info/RECORD
pyconza2014-0.2.10.dist-info/top_level.txt
pyconza2014-0.2.10.dist-info/WHEEL
