Metadata-Version: 2.0
Name: pyconza2014
Version: 0.2.10
Summary: PyConZA 2014 Demo
Home-page: https://github.com/michaeljoseph/pyconza2014
Author: Michael Joseph
Author-email: michaeljoseph@gmail.com
License: Apache License
Requires-Dist: click (<2.1.0)
